<?xml version="1.0" encoding="utf-8"?>
<templates id="template" xml:space="preserve">
    <!--  Inherit navbar  -->
    <t t-inherit="web.NavBar" t-inherit-mode="extension" owl="1">
        
    </t>
    <t t-inherit="web.NavBar.AppsMenu" t-inherit-mode="extension" owl="1">
        <xpath expr="//Dropdown" position="replace">
            <li class="dropdown">
                <a id="openSidebar" style="display: block; cursor: pointer;"
                   t-ref="openSidebar">
                    <i class="fa fa-bars fa-lg"/>
                </a>
                <a id="closeSidebar" style="display: none; cursor: pointer;"
                   t-ref="closeSidebar">
                    <i class="fa fa-bars fa-lg"/>
                </a>
            </li>
        </xpath>
    </t>
    <t t-inherit="web.UserMenu" t-inherit-mode="extension" owl="1">
        
    </t>
</templates>
